re_assert.py
re_assert-1.1.0.dist-info/LICENSE
re_assert-1.1.0.dist-info/METADATA
re_assert-1.1.0.dist-info/WHEEL
re_assert-1.1.0.dist-info/top_level.txt
re_assert-1.1.0.dist-info/RECORD
