Metadata-Version: 2.1
Name: re-assert
Version: 1.1.0
Summary: show where your regex match assertion failed!
Home-page: https://github.com/asottile/re-assert
Author: Anthony Sottile
Author-email: asottile@umich.edu
License: MIT
Platform: UNKNOWN
Classifier: License :: OSI Approved :: MIT License
Classifier: Programming Language :: Python :: 3
Classifier: Programming Language :: Python :: 3 :: Only
Classifier: Programming Language :: Python :: 3.6
Classifier: Programming Language :: Python :: 3.7
Classifier: Programming Language :: Python :: 3.8
Requires-Python: >=3.6.1
Requires-Dist: regex
